README.txt
setup.py
docs/HISTORY.txt
plone/__init__.py
plone.controller.egg-info/PKG-INFO
plone.controller.egg-info/SOURCES.txt
plone.controller.egg-info/dependency_links.txt
plone.controller.egg-info/entry_points.txt
plone.controller.egg-info/namespace_packages.txt
plone.controller.egg-info/not-zip-safe
plone.controller.egg-info/requires.txt
plone.controller.egg-info/top_level.txt
plone/controller/Notebook.py
plone/controller/__init__.py
plone/controller/aboutDialog.py
plone/controller/config.py
plone/controller/configPage.py
plone/controller/controller.py
plone/controller/guageApp.py
plone/controller/plone.icns
plone/controller/states.py
plone/controller/status.py
plone/controller/statusPage.py
plone/controller/statusPosix.py
plone/controller/version.txt
plone/controller/images/plone-icon.png
plone/controller/images/plone.ico