Metadata-Version: 1.0
Name: plone.controller
Version: 1.8
Summary: Controller for starting/stopping Plone services
Home-page: http://plone.org/products/plone/
Author: The Plone Collective
Author-email: plone-developers@lists.sourceforge.net
License: GPL
Keywords: controller plone
Platform: UNKNOWN
Classifier: Programming Language :: Python
Classifier: Topic :: Software Development :: Libraries :: Python Modules
